[
  {
    "id": 1,
    "gender":"female",
    "name": "Hira Singh",
    "image": "https://www.thefamouspeople.com/profiles/thumbs/hazel-keech-1.jpg",
    "occupation": "UX Designer",
    "location": "Columbia",
    "email": "darrell.carr@example.com",
    "age": 37,
    "phone": "(316)-925-1000"
  
  },
  {
    "id": 2,
    "gender":"male",
    "name": "James Lee",
    "image": "https://ca-times.brightspotcdn.com/dims4/default/5d2bb98/2147483647/strip/true/crop/2048x1365+0+0/resize/840x560!/quality/90/?url=https%3A%2F%2Fwww.trbimg.com%2Fimg-5b69d7e2%2Fturbine%2Fsns-201808070032--tms--celebtrvctnct-a20180807-a-20180807",
    "occupation": "Product Owner",
    "location": "Jersey City",
    "email": "james.lee@example.com",
    "age": 34,
    "phone": "(316)-925-1001"
  
  },
  
    {
     "id":3,
    "gender": "male",
    "name": "Darrell Carr",
    "image":"https://bloximages.newyork1.vip.townnews.com/gazette.com/content/tncms/assets/v3/editorial/2/d5/2d58cbca-f8ce-11e8-82e0-f3256a23a61e/5c08381d64ab7.image.jpg",
    "occupation": "Developer",
    "location": "Omaha",
    "email": "darrell.carr@example.com",
    "age": 28,
    "phone": "(316)-925-1002"
  
  },
  {
    "id":4,
   "gender": "Feale",
   "name": "Leslie Floor",
   "image":  "https://randomuser.me/api/portraits/med/women/88.jpg",
   "occupation": "Developer",
   "location": "Omaha",
   "email": "jamie.gordon@example.com",
   "age": 37,
   "phone": "(316)-925-1004"
 
 },
 {
  "id":5,
 "gender": "male",
 "name": "Clinton Allen",
 "image": "https://randomuser.me/api/portraits/med/men/85.jpg",
 "occupation": "Developer",
 "location": "Omaha",
 "email": "clinton.allen@example.com",
 "age": 41,
 "phone": "(316)-925-1005"

},
{
  "id":6,
 "gender": "male",
 "name": "Darrell Carlos",
 "image":"https://randomuser.me/api/portraits/men/5.jpg",
 "occupation": "Operations",
 "location": "New York",
 "email": "darrell.carlos@example.com",
 "age": 57,
 "phone": "(316)-925-1006"

},
{
  "id":7,
 "gender": "male",
 "name": "Jamie Wough",
 "image":"https://randomuser.me/api/portraits/med/men/80.jpg",
 "occupation": "Developer",
 "location": "Omaha",
 "email": "jamie.wough@example.com",
 "age": 42,
 "phone": "(316)-925-1007"

},
{
  "id":8,
 "gender": "female",
 "name": "Leslie Bailey",
 "image":"https://randomuser.me/api/portraits/med/women/79.jpg",
 "occupation": "Developer",
 "location": "Omaha",
 "email": "leslie.bailey@example.com",
 "age": 32,
 "phone": "(316)-925-1008"

},
{
  "id":9,
 "gender": "female",
 "name": "Tiffany Franklin",
 "image": "https://randomuser.me/api/portraits/med/women/67.jpg",
 "occupation": "Developer",
 "location": "Omaha",
 "email": "tiffany.franklin@example.com",
 "age": 27,
 "phone": "(316)-925-1009"

}
]